educationwarehouse/__init__.py
educationwarehouse-0.0.0.dist-info/entry_points.txt
educationwarehouse-0.0.0.dist-info/WHEEL
educationwarehouse-0.0.0.dist-info/METADATA
educationwarehouse-0.0.0.dist-info/RECORD
